{
  "articles": {
    "overall_success": false,
    "success_percent": 0.0,
    "total_expectations": 28,
    "successful_expectations": 0,
    "failed_expectations_count": 28,
    "failed_expectations": [
      {
        "expectation_type": "expect_column_to_exist",
        "column": null,
        "observed_value": "N/A",
        "details": {
          "missing_count": 1
        }
      },
      {
        "expectation_type": "expect_column_to_exist",
        "column": null,
        "observed_value": "N/A",
        "details": {
          "missing_count": 1
        }
      },
      {
        "expectation_type": "expect_column_to_exist",
        "column": null,
        "observed_value": "N/A",
        "details": {
          "missing_count": 1
        }
      },
      {
        "expectation_type": "expect_column_to_exist",
        "column": null,
        "observed_value": "N/A",
        "details": {
          "missing_count": 1
        }
      },
      {
        "expectation_type": "expect_column_to_exist",
        "column": null,
        "observed_value": "N/A",
        "details": {
          "missing_count": 1
        }
      },
      {
        "expectation_type": "expect_column_to_exist",
        "column": null,
        "observed_value": "N/A",
        "details": {
          "missing_count": 1
        }
      },
      {
        "expectation_type": "expect_column_values_to_be_of_type",
        "column": null,
        "observed_value": "N/A",
        "details": {}
      },
      {
        "expectation_type": "expect_column_values_to_be_of_type",
        "column": null,
        "observed_value": "N/A",
        "details": {}
      },
      {
        "expectation_type": "expect_column_values_to_be_of_type",
        "column": null,
        "observed_value": "N/A",
        "details": {}
      },
      {
        "expectation_type": "expect_column_values_to_be_of_type",
        "column": null,
        "observed_value": "N/A",
        "details": {}
      },
      {
        "expectation_type": "expect_column_values_to_not_be_null",
        "column": null,
        "observed_value": "N/A",
        "details": {}
      },
      {
        "expectation_type": "expect_column_values_to_not_be_null",
        "column": null,
        "observed_value": "N/A",
        "details": {}
      },
      {
        "expectation_type": "expect_column_values_to_not_be_null",
        "column": null,
        "observed_value": "N/A",
        "details": {}
      },
      {
        "expectation_type": "expect_column_values_to_not_be_null",
        "column": null,
        "observed_value": "N/A",
        "details": {}
      },
      {
        "expectation_type": "expect_column_values_to_not_be_null",
        "column": null,
        "observed_value": "N/A",
        "details": {}
      },
      {
        "expectation_type": "expect_column_values_to_not_be_null",
        "column": null,
        "observed_value": "N/A",
        "details": {}
      },
      {
        "expectation_type": "expect_column_values_to_match_regex",
        "column": null,
        "observed_value": "N/A",
        "details": {}
      },
      {
        "expectation_type": "expect_column_values_to_match_regex",
        "column": null,
        "observed_value": "N/A",
        "details": {}
      },
      {
        "expectation_type": "expect_column_values_to_match_regex",
        "column": null,
        "observed_value": "N/A",
        "details": {}
      },
      {
        "expectation_type": "expect_column_values_to_be_between",
        "column": null,
        "observed_value": "N/A",
        "details": {}
      },
      {
        "expectation_type": "expect_column_values_to_be_between",
        "column": null,
        "observed_value": "N/A",
        "details": {}
      },
      {
        "expectation_type": "expect_column_values_to_be_between",
        "column": null,
        "observed_value": "N/A",
        "details": {}
      },
      {
        "expectation_type": "expect_column_values_to_not_be_null",
        "column": null,
        "observed_value": "N/A",
        "details": {}
      },
      {
        "expectation_type": "expect_column_values_to_not_be_null",
        "column": null,
        "observed_value": "N/A",
        "details": {}
      },
      {
        "expectation_type": "expect_column_value_lengths_to_be_between",
        "column": null,
        "observed_value": "N/A",
        "details": {}
      },
      {
        "expectation_type": "expect_column_value_lengths_to_be_between",
        "column": null,
        "observed_value": "N/A",
        "details": {}
      },
      {
        "expectation_type": "expect_column_value_lengths_to_be_between",
        "column": null,
        "observed_value": "N/A",
        "details": {}
      },
      {
        "expectation_type": "expect_column_values_to_be_of_type",
        "column": null,
        "observed_value": "N/A",
        "details": {}
      }
    ],
    "threshold": 95.0,
    "timestamp": "2025-08-28T18:54:30.095687",
    "suite_name": "articles",
    "run_id": "batch_validation_20250828_185430"
  },
  "ask_requests": {
    "overall_success": false,
    "success_percent": 10.0,
    "total_expectations": 10,
    "successful_expectations": 1,
    "failed_expectations_count": 9,
    "failed_expectations": [
      {
        "expectation_type": "expect_column_to_exist",
        "column": null,
        "observed_value": "N/A",
        "details": {
          "missing_count": 1
        }
      },
      {
        "expectation_type": "expect_column_values_to_be_of_type",
        "column": null,
        "observed_value": "N/A",
        "details": {}
      },
      {
        "expectation_type": "expect_column_values_to_be_of_type",
        "column": null,
        "observed_value": "N/A",
        "details": {}
      },
      {
        "expectation_type": "expect_column_values_to_not_be_null",
        "column": null,
        "observed_value": "N/A",
        "details": {}
      },
      {
        "expectation_type": "expect_column_value_lengths_to_be_between",
        "column": null,
        "observed_value": "N/A",
        "details": {}
      },
      {
        "expectation_type": "expect_column_values_to_be_between",
        "column": null,
        "observed_value": "N/A",
        "details": {}
      },
      {
        "expectation_type": "expect_column_values_to_match_regex",
        "column": null,
        "observed_value": "N/A",
        "details": {}
      },
      {
        "expectation_type": "expect_column_values_to_match_regex",
        "column": null,
        "observed_value": "N/A",
        "details": {}
      },
      {
        "expectation_type": "expect_column_values_to_match_regex",
        "column": null,
        "observed_value": "N/A",
        "details": {}
      }
    ],
    "threshold": 95.0,
    "timestamp": "2025-08-28T18:54:30.101555",
    "suite_name": "ask_requests",
    "run_id": "batch_validation_20250828_185430"
  }
}
