{
  "analysis_metadata": {
    "timestamp": "2025-08-15T00:07:37.444137+00:00",
    "analyzer_model": "distilbert-base-uncased-finetuned-sst-2-english",
    "total_articles_analyzed": 5
  },
  "article_results": [
    {
      "article_id": "sentiment_tech_1",
      "title": "Apple Reports Record-Breaking Q4 Earnings",
      "topic": "Technology",
      "source": "TechNews Today",
      "published_at": "2024-10-30T16:00:00Z",
      "title_sentiment": {
        "label": "POSITIVE",
        "score": 0.997
      },
      "content_sentiment": {
        "label": "POSITIVE",
        "score": 1.0
      },
      "overall_sentiment": {
        "label": "POSITIVE",
        "score": 0.999
      },
      "analysis_timestamp": "2025-08-15T00:07:35.718287+00:00"
    },
    {
      "article_id": "sentiment_market_1",
      "title": "Global Markets Face Uncertainty Amid Economic Concerns",
      "topic": "Finance",
      "source": "Financial Times",
      "published_at": "2024-10-30T14:30:00Z",
      "title_sentiment": {
        "label": "NEGATIVE",
        "score": 0.973
      },
      "content_sentiment": {
        "label": "NEGATIVE",
        "score": 0.99
      },
      "overall_sentiment": {
        "label": "NEGATIVE",
        "score": 0.984
      },
      "analysis_timestamp": "2025-08-15T00:07:36.501375+00:00"
    },
    {
      "article_id": "sentiment_health_1",
      "title": "Breakthrough Medical Research Offers Hope for Cancer Patients",
      "topic": "Healthcare",
      "source": "Medical Journal Today",
      "published_at": "2024-10-30T12:00:00Z",
      "title_sentiment": {
        "label": "POSITIVE",
        "score": 1.0
      },
      "content_sentiment": {
        "label": "POSITIVE",
        "score": 1.0
      },
      "overall_sentiment": {
        "label": "POSITIVE",
        "score": 1.0
      },
      "analysis_timestamp": "2025-08-15T00:07:36.781900+00:00"
    },
    {
      "article_id": "sentiment_climate_1",
      "title": "Climate Change Report Reveals Alarming Temperature Trends",
      "topic": "Environment",
      "source": "Environmental Science Daily",
      "published_at": "2024-10-30T10:15:00Z",
      "title_sentiment": {
        "label": "NEGATIVE",
        "score": 0.822
      },
      "content_sentiment": {
        "label": "POSITIVE",
        "score": 0.818
      },
      "overall_sentiment": {
        "label": "POSITIVE",
        "score": 0.818
      },
      "analysis_timestamp": "2025-08-15T00:07:37.049906+00:00"
    },
    {
      "article_id": "sentiment_neutral_1",
      "title": "New Transportation Infrastructure Project Announced",
      "topic": "Infrastructure",
      "source": "Government News",
      "published_at": "2024-10-30T09:00:00Z",
      "title_sentiment": {
        "label": "POSITIVE",
        "score": 0.992
      },
      "content_sentiment": {
        "label": "POSITIVE",
        "score": 0.82
      },
      "overall_sentiment": {
        "label": "POSITIVE",
        "score": 0.872
      },
      "analysis_timestamp": "2025-08-15T00:07:37.196256+00:00"
    }
  ],
  "trend_analysis": {
    "total_articles": 5,
    "sentiment_distribution": {
      "POSITIVE": 4,
      "NEGATIVE": 1,
      "NEUTRAL": 0
    },
    "sentiment_percentages": {
      "POSITIVE": 80.0,
      "NEGATIVE": 20.0,
      "NEUTRAL": 0.0
    },
    "average_score": 0.9346,
    "topic_analysis": {
      "Technology": {
        "POSITIVE": 1,
        "NEGATIVE": 0,
        "NEUTRAL": 0,
        "scores": [
          0.999
        ]
      },
      "Finance": {
        "POSITIVE": 0,
        "NEGATIVE": 1,
        "NEUTRAL": 0,
        "scores": [
          0.984
        ]
      },
      "Healthcare": {
        "POSITIVE": 1,
        "NEGATIVE": 0,
        "NEUTRAL": 0,
        "scores": [
          1.0
        ]
      },
      "Environment": {
        "POSITIVE": 1,
        "NEGATIVE": 0,
        "NEUTRAL": 0,
        "scores": [
          0.818
        ]
      },
      "Infrastructure": {
        "POSITIVE": 1,
        "NEGATIVE": 0,
        "NEUTRAL": 0,
        "scores": [
          0.872
        ]
      }
    },
    "source_analysis": {
      "TechNews Today": {
        "POSITIVE": 1,
        "NEGATIVE": 0,
        "NEUTRAL": 0
      },
      "Financial Times": {
        "POSITIVE": 0,
        "NEGATIVE": 1,
        "NEUTRAL": 0
      },
      "Medical Journal Today": {
        "POSITIVE": 1,
        "NEGATIVE": 0,
        "NEUTRAL": 0
      },
      "Environmental Science Daily": {
        "POSITIVE": 1,
        "NEGATIVE": 0,
        "NEUTRAL": 0
      },
      "Government News": {
        "POSITIVE": 1,
        "NEGATIVE": 0,
        "NEUTRAL": 0
      }
    }
  }
}